r00tinder/__init__.py
r00tinder/cli.py
r00tinder/main.py
r00tinder/files/sniffer/all_protos.desc
r00tinder/files/sniffer/protobuf_definitions.pb
r00tinder/files/sniffer/certs/mitmproxy-ca-cert2.cer
r00tinder/files/sniffer/flows/capture-invalid-gps.mitm
r00tinder/files/sniffer/proto/platform.proto.bak
r00tinder/files/sniffer/proto/tinder-data.proto
r00tinder/files/sniffer/proto/google/protobuf/any.proto
r00tinder/files/sniffer/proto/google/protobuf/api.proto
r00tinder/files/sniffer/proto/google/protobuf/descriptor.proto
r00tinder/files/sniffer/proto/google/protobuf/duration.proto
r00tinder/files/sniffer/proto/google/protobuf/empty.proto
r00tinder/files/sniffer/proto/google/protobuf/field_mask.proto
r00tinder/files/sniffer/proto/google/protobuf/source_context.proto
r00tinder/files/sniffer/proto/google/protobuf/struct.proto
r00tinder/files/sniffer/proto/google/protobuf/timestamp.proto
r00tinder/files/sniffer/proto/google/protobuf/type.proto
r00tinder/files/sniffer/proto/google/protobuf/wrappers.proto
r00tinder/files/sniffer/proto/google/protobuf/compiler/plugin.proto
r00tinder/files/sniffer/proto/tinder/api/biblio/v1/biblio_api.proto
r00tinder/files/sniffer/proto/tinder/api/biblio/v1/biblio_list_item.proto
r00tinder/files/sniffer/proto/tinder/api/biblio/v1/biblio_section.proto
r00tinder/files/sniffer/proto/tinder/api/biblio/v1/spotify_data.proto
r00tinder/files/sniffer/proto/tinder/api/sharemydate/v1/share_my_date_api.proto
r00tinder/files/sniffer/proto/tinder/api/tinderu/v3/request/send_otp_email_request.proto
r00tinder/files/sniffer/proto/tinder/api/tinderu/v3/request/validate_email_otp_request.proto
r00tinder/files/sniffer/proto/tinder/api/tinderu/v3/response/error.proto
r00tinder/files/sniffer/proto/tinder/api/tinderu/v3/response/send_otp_email_response.proto
r00tinder/files/sniffer/proto/tinder/api/tinderu/v3/response/validate_email_otp_response.proto
r00tinder/files/sniffer/proto/tinder/api/tinderu/v3/response/verify_email_eligible_response.proto
r00tinder-0.1.1.dist-info/METADATA
r00tinder-0.1.1.dist-info/WHEEL
r00tinder-0.1.1.dist-info/entry_points.txt
r00tinder-0.1.1.dist-info/RECORD
