Metadata-Version: 2.4
Name: r00tinder
Version: 0.1.1
Summary: Add your description here
Requires-Python: >=3.10
Requires-Dist: paramiko
Requires-Dist: prettytable
Requires-Dist: pytz
Requires-Dist: questionary
Requires-Dist: r00adb>=0.1.3
Requires-Dist: r00android-fake
Requires-Dist: r00android-init
Requires-Dist: r00android-patch
Requires-Dist: r00arango-connector
Requires-Dist: r00docker
Requires-Dist: r00flash
Requires-Dist: r00logger
Requires-Dist: r00proxy
Requires-Dist: r00richi
Requires-Dist: r00secret
Requires-Dist: r00server
Requires-Dist: r00system
Requires-Dist: r00textutil
